goco/__init__.py
goco/goco.py
goco-1.0.6.dist-info/LICENSE
goco-1.0.6.dist-info/METADATA
goco-1.0.6.dist-info/WHEEL
goco-1.0.6.dist-info/top_level.txt
goco-1.0.6.dist-info/RECORD
