Metadata-Version: 2.1
Name: goco
Version: 1.0.6
Summary: Simple authenticator for google apis
Home-page: https://github.com/elmoiv/goco
Author: elmoiv
Author-email: elmoiv@yahoo.com
License: UNKNOWN
Platform: UNKNOWN
Classifier: Programming Language :: Python :: 3
Classifier: License :: OSI Approved :: MIT License
Classifier: Operating System :: OS Independent
Requires-Python: >=3.4
Requires-Dist: requests
Requires-Dist: httplib2
Requires-Dist: google-api-python-client
Requires-Dist: oauth2client
